xss_scan/__init__.py
xss_scan/main.py
xss_scan/includes/__init__.py
xss_scan/includes/bot.py
xss_scan/includes/config.py
xss_scan/includes/filereader.py
xss_scan/includes/scan.py
xss_scan/includes/writefile.py
xss_scan/utils/__init__.py
xss_scan/utils/configure.py
xss_scan/utils/const.py
xss_scan/utils/helpers.py
xss_scan-1.0.1.dist-info/METADATA
xss_scan-1.0.1.dist-info/WHEEL
xss_scan-1.0.1.dist-info/entry_points.txt
xss_scan-1.0.1.dist-info/top_level.txt
xss_scan-1.0.1.dist-info/RECORD
